openplugincore/__init__.py
openplugincore/openplugin.py
openplugincore/openplugin_completion.py
openplugincore/openplugin_memo.py
openplugincore/types.py
openplugincore/utils/__init__.py
openplugincore/utils/constants.py
openplugincore/utils/prompting.py
tests/__init__.py
tests/mock_data.py
tests/test_e2e.py
tests/test_openplugin.py
tests/test_openplugin_completion.py
tests/test_openplugin_memo.py
openplugincore-0.7.3.dist-info/METADATA
openplugincore-0.7.3.dist-info/WHEEL
openplugincore-0.7.3.dist-info/top_level.txt
openplugincore-0.7.3.dist-info/RECORD
