Metadata-Version: 2.1
Name: openplugincore
Version: 0.7.3
Summary: Seamlessly integrate with OpenAI ChatGPT plugins via API (or client), offering the same powerful functionality as the ChatGPT api + plugins!
Home-page: UNKNOWN
Author: Sebastian Sosa
Author-email: 1sebastian1sosa1@gmail.com
License: UNKNOWN
Keywords: python,openai,chatgpt,chat,plugin
Platform: UNKNOWN
Classifier: Development Status :: 2 - Pre-Alpha
Classifier: Intended Audience :: Developers
Classifier: Programming Language :: Python :: 3.10
Classifier: Programming Language :: Python :: 3
Classifier: Operating System :: MacOS :: MacOS X
Classifier: Operating System :: Microsoft :: Windows
Requires-Dist: requests
Requires-Dist: openai
Requires-Dist: oplangchain
Requires-Dist: python-dotenv
